{"_id":{"$oid":"5d07a7588d2b86775084ce86"},"author1":{"$oid":"5d06094b046848a0fe30f474"},"author2":{"$oid":"5d04abfda4b183c7cbe98292"},"date":{"$date":"2019-06-17T14:44:40.683Z"},"chat":[{"_id":{"$oid":"5d07a7ba45b5d979b7828ea1"},"createdAt":{"$date":"2019-06-17T14:46:18.907Z"},"detail":"fuck chet me thang vu anh","type":"text","seen":false,"auth":{"$oid":"5d06094b046848a0fe30f474"}},{"_id":{"$oid":"5d07a7c045b5d979b7828ea2"},"createdAt":{"$date":"2019-06-17T14:46:24.408Z"},"detail":"fuck chet me thang vu anh","type":"text","seen":false,"auth":{"$oid":"5d06094b046848a0fe30f474"}},{"_id":{"$oid":"5d07a7c145b5d979b7828ea3"},"createdAt":{"$date":"2019-06-17T14:46:25.346Z"},"detail":"fuck chet me thang vu anh","type":"text","seen":false,"auth":{"$oid":"5d06094b046848a0fe30f474"}},{"_id":{"$oid":"5d07a7ca45b5d979b7828ea4"},"createdAt":{"$date":"2019-06-17T14:46:34.751Z"},"detail":"fuck chet me thang vu anh ddm thang khanh ","type":"text","seen":false,"auth":{"$oid":"5d06094b046848a0fe30f474"}},{"_id":{"$oid":"5d07a7ea45b5d979b7828ea5"},"createdAt":{"$date":"2019-06-17T14:47:06.534Z"},"detail":"duong is da best ","type":"text","seen":false,"auth":{"$oid":"5d07a7588d2b86775084ce86"}},{"_id":{"$oid":"5d07a7eb45b5d979b7828ea6"},"createdAt":{"$date":"2019-06-17T14:47:07.229Z"},"detail":"duong is da best ","type":"text","seen":false,"auth":{"$oid":"5d07a7588d2b86775084ce86"}},{"_id":{"$oid":"5d07a7eb45b5d979b7828ea7"},"createdAt":{"$date":"2019-06-17T14:47:07.768Z"},"detail":"duong is da best ","type":"text","seen":false,"auth":{"$oid":"5d07a7588d2b86775084ce86"}},{"_id":{"$oid":"5d07a7ec45b5d979b7828ea8"},"createdAt":{"$date":"2019-06-17T14:47:08.217Z"},"detail":"duong is da best ","type":"text","seen":false,"auth":{"$oid":"5d07a7588d2b86775084ce86"}}],"__v":8,"lastMessage":{"$date":"2019-06-17T14:47:08.217Z"}}
{"_id":{"$oid":"5d07a76f8d2b86775084ce87"},"author1":{"$oid":"5d06094b046848a0fe30f474"},"author2":{"$oid":"5d07474acb0c78cf6f14cf0a"},"date":{"$date":"2019-06-17T14:45:03.967Z"},"chat":[{"_id":{"$oid":"5d07a80f45b5d979b7828ea9"},"createdAt":{"$date":"2019-06-17T14:47:43.514Z"},"detail":"vu co la thang cho","type":"text","seen":false,"auth":{"$oid":"5d06094b046848a0fe30f474"}},{"_id":{"$oid":"5d07a81045b5d979b7828eaa"},"createdAt":{"$date":"2019-06-17T14:47:44.276Z"},"detail":"vu co la thang cho","type":"text","seen":false,"auth":{"$oid":"5d06094b046848a0fe30f474"}},{"_id":{"$oid":"5d07a81045b5d979b7828eab"},"createdAt":{"$date":"2019-06-17T14:47:44.779Z"},"detail":"vu co la thang cho","type":"text","seen":false,"auth":{"$oid":"5d06094b046848a0fe30f474"}},{"_id":{"$oid":"5d07a81245b5d979b7828eac"},"createdAt":{"$date":"2019-06-17T14:47:46.260Z"},"detail":"vu co la thang cho","type":"text","seen":false,"auth":{"$oid":"5d06094b046848a0fe30f474"}},{"_id":{"$oid":"5d07a81245b5d979b7828ead"},"createdAt":{"$date":"2019-06-17T14:47:46.472Z"},"detail":"vu co la thang cho","type":"text","seen":false,"auth":{"$oid":"5d06094b046848a0fe30f474"}},{"_id":{"$oid":"5d07a83945b5d979b7828eae"},"createdAt":{"$date":"2019-06-17T14:48:25.511Z"},"detail":"vcl dmm vlxx","type":"text","seen":false,"auth":{"$oid":"5d07474acb0c78cf6f14cf0a"}},{"_id":{"$oid":"5d07a83a45b5d979b7828eaf"},"createdAt":{"$date":"2019-06-17T14:48:26.252Z"},"detail":"vcl dmm vlxx","type":"text","seen":false,"auth":{"$oid":"5d07474acb0c78cf6f14cf0a"}},{"_id":{"$oid":"5d07a83a45b5d979b7828eb0"},"createdAt":{"$date":"2019-06-17T14:48:26.590Z"},"detail":"vcl dmm vlxx","type":"text","seen":false,"auth":{"$oid":"5d07474acb0c78cf6f14cf0a"}},{"_id":{"$oid":"5d07a83a45b5d979b7828eb1"},"createdAt":{"$date":"2019-06-17T14:48:26.838Z"},"detail":"vcl dmm vlxx","type":"text","seen":false,"auth":{"$oid":"5d07474acb0c78cf6f14cf0a"}},{"_id":{"$oid":"5d07a83b45b5d979b7828eb2"},"createdAt":{"$date":"2019-06-17T14:48:27.037Z"},"detail":"vcl dmm vlxx","type":"text","seen":false,"auth":{"$oid":"5d07474acb0c78cf6f14cf0a"}},{"_id":{"$oid":"5d07a83b45b5d979b7828eb3"},"createdAt":{"$date":"2019-06-17T14:48:27.227Z"},"detail":"vcl dmm vlxx","type":"text","seen":false,"auth":{"$oid":"5d07474acb0c78cf6f14cf0a"}},{"_id":{"$oid":"5d07a83b45b5d979b7828eb4"},"createdAt":{"$date":"2019-06-17T14:48:27.396Z"},"detail":"vcl dmm vlxx","type":"text","seen":false,"auth":{"$oid":"5d07474acb0c78cf6f14cf0a"}},{"_id":{"$oid":"5d07a83b45b5d979b7828eb5"},"createdAt":{"$date":"2019-06-17T14:48:27.578Z"},"detail":"vcl dmm vlxx","type":"text","seen":false,"auth":{"$oid":"5d07474acb0c78cf6f14cf0a"}},{"_id":{"$oid":"5d07a83b45b5d979b7828eb6"},"createdAt":{"$date":"2019-06-17T14:48:27.817Z"},"detail":"vcl dmm vlxx","type":"text","seen":false,"auth":{"$oid":"5d07474acb0c78cf6f14cf0a"}}],"__v":14,"lastMessage":{"$date":"2019-06-17T14:48:27.817Z"}}
